jaraco/mongodb/__init__.py
jaraco/mongodb/check-gridfs.py
jaraco/mongodb/cli.py
jaraco/mongodb/codec.py
jaraco/mongodb/compat.py
jaraco/mongodb/fields.py
jaraco/mongodb/fixtures.py
jaraco/mongodb/helper.py
jaraco/mongodb/insert-doc.py
jaraco/mongodb/install.py
jaraco/mongodb/manage.py
jaraco/mongodb/migration.py
jaraco/mongodb/monitor-index-creation.py
jaraco/mongodb/move-gridfs.py
jaraco/mongodb/oplog.py
jaraco/mongodb/pmxbot.py
jaraco/mongodb/query.py
jaraco/mongodb/repair-gridfs.py
jaraco/mongodb/sampling.py
jaraco/mongodb/service.py
jaraco/mongodb/sessions.py
jaraco/mongodb/sharding.py
jaraco/mongodb/testing.py
jaraco/mongodb/timers.py
jaraco/mongodb/uri.py
jaraco_mongodb-12.4.0.dist-info/licenses/LICENSE
jaraco_mongodb-12.4.0.dist-info/METADATA
jaraco_mongodb-12.4.0.dist-info/WHEEL
jaraco_mongodb-12.4.0.dist-info/entry_points.txt
jaraco_mongodb-12.4.0.dist-info/top_level.txt
jaraco_mongodb-12.4.0.dist-info/RECORD
