Metadata-Version: 2.4
Name: jaraco.mongodb
Version: 12.4.0
Summary: Routines and classes supporting MongoDB environments
Author-email: "Jason R. Coombs" <jaraco@jaraco.com>
Project-URL: Source, https://github.com/jaraco/jaraco.mongodb
Classifier: Development Status :: 5 - Production/Stable
Classifier: Intended Audience :: Developers
Classifier: Programming Language :: Python :: 3
Classifier: Programming Language :: Python :: 3 :: Only
Classifier: Framework :: Pytest
Requires-Python: >=3.9
License-File: LICENSE
Requires-Dist: pymongo>=3.5
Requires-Dist: python-dateutil
Requires-Dist: jaraco.services>=2
Requires-Dist: portend
Requires-Dist: jaraco.itertools>=2
Requires-Dist: jaraco.functools>=2
Requires-Dist: jaraco.ui>=2.4
Requires-Dist: jaraco.context>=2
Requires-Dist: more_itertools
Requires-Dist: jaraco.logging>=2
Requires-Dist: tempora
Requires-Dist: pytimeparse
Requires-Dist: jaraco.collections>=2
Requires-Dist: cachetools
Requires-Dist: backports.tarfile; python_version < "3.12"
Requires-Dist: dnspython[wmi]
Provides-Extra: test
Requires-Dist: pytest!=8.1.*,>=6; extra == "test"
Requires-Dist: cherrypy; extra == "test"
Provides-Extra: doc
Requires-Dist: sphinx>=3.5; extra == "doc"
Requires-Dist: jaraco.packaging>=9.3; extra == "doc"
Requires-Dist: rst.linker>=1.9; extra == "doc"
Requires-Dist: furo; extra == "doc"
Requires-Dist: sphinx-lint; extra == "doc"
Requires-Dist: cherrypy; extra == "doc"
Provides-Extra: check
Requires-Dist: pytest-checkdocs>=2.4; extra == "check"
Requires-Dist: pytest-ruff>=0.2.1; sys_platform != "cygwin" and extra == "check"
Provides-Extra: cover
Requires-Dist: pytest-cov; extra == "cover"
Provides-Extra: enabler
Requires-Dist: pytest-enabler>=2.2; extra == "enabler"
Provides-Extra: type
Requires-Dist: pytest-mypy; extra == "type"
Requires-Dist: types-python-dateutil; extra == "type"
Requires-Dist: types-cachetools; extra == "type"
Dynamic: license-file
